slacks/__init__.py
slacks/custom_exceptions.py
slacks/slacks.py
slacks-0.0.1.dist-info/LICENSE
slacks-0.0.1.dist-info/METADATA
slacks-0.0.1.dist-info/WHEEL
slacks-0.0.1.dist-info/top_level.txt
slacks-0.0.1.dist-info/RECORD
