Metadata-Version: 2.1
Name: slacks
Version: 0.0.1
Summary: CLI utility for slack notifications
Home-page: https://github.com/hicdss/slacks
Author: Wojciech Puchta, Hicron DSS
Author-email: wojciech.puchta@hicron.com
License: UNKNOWN
Platform: UNKNOWN
Classifier: Programming Language :: Python :: 3
Classifier: License :: OSI Approved :: MIT License
Classifier: Operating System :: OS Independent
